netcbs/__init__.py
netcbs/_version.py
netcbs/create_synthetic_data.py
netcbs/netcbs.py
netcbs-0.3.1.dist-info/licenses/LICENSE
netcbs-0.3.1.dist-info/METADATA
netcbs-0.3.1.dist-info/WHEEL
netcbs-0.3.1.dist-info/top_level.txt
netcbs-0.3.1.dist-info/RECORD
