Metadata-Version: 2.4
Name: netcbs
Version: 0.3.1
Summary: Package to create aggregated variables from CBS network data
Author-email: Javier Garcia-Bernardo <j.garciabernardo@uu.nl>
License: MIT License
Project-URL: homepage, https://github.com/sodascience/netcbs
Project-URL: repository, https://github.com/sodascience/netcbs
Keywords: popnet,cbs,network data,netcbs
Classifier: Programming Language :: Python :: 3
Classifier: Programming Language :: Python :: 3.8
Classifier: Programming Language :: Python :: 3.9
Classifier: Programming Language :: Python :: 3.10
Classifier: Programming Language :: Python :: 3.11
Classifier: Programming Language :: Python :: 3.12
Classifier: Programming Language :: Python :: 3.13
Classifier: Operating System :: OS Independent
Requires-Python: >=3.8
License-File: LICENSE
Requires-Dist: polars>=1.0
Requires-Dist: pandas
Requires-Dist: duckdb
Requires-Dist: pyarrow
Requires-Dist: numpy
Provides-Extra: test
Requires-Dist: ruff; extra == "test"
Requires-Dist: pytest; extra == "test"
Requires-Dist: mypy; extra == "test"
Dynamic: license-file
